kres/main.py
kres/api/apiHandler.py
kres/api/kresApi.py
kres/api/kresApiLauncher.py
kres/config/extractConfig.py
kres/config/loadConfig.py
kres/encryption/tokenEncryption.py
kres/subparsers/accessParser.py
kres/subparsers/apiParser.py
kres/subparsers/initParser.py
kres/subparsers/logoutParser.py
kres/subparsers/restartParser.py
kres/utils/checkPortStatus.py
kres/utils/deleteDir.py
kres/utils/extractResourceNames.py
kres/utils/logger.py
kres/utils/parser.py
kres/utils/readMemory.py
kres/utils/stopKresApi.py
kres-1.0.1.dist-info/METADATA
kres-1.0.1.dist-info/WHEEL
kres-1.0.1.dist-info/entry_points.txt
kres-1.0.1.dist-info/top_level.txt
kres-1.0.1.dist-info/RECORD
