Metadata-Version: 2.4
Name: kres
Version: 1.0.1
Summary: Kubernetes Resource Restarter
Author-email: Shashank Palla <shashankpalla44@gmail.com>
Requires-Python: >=3.7
Requires-Dist: pyyaml>=6.0.1
Requires-Dist: requests==2.32.4
Requires-Dist: cryptography==45.0.5
Requires-Dist: fastapi==0.116.1
Requires-Dist: uvicorn==0.35.0
